pnostic/__init__.py
pnostic/structure.py
pnostic/utils.py
pnostic/envelopers/LiveGraph.py
pnostic/envelopers/__init__.py
pnostic/loggers/CSVOverZealous.py
pnostic/loggers/Printr.py
pnostic/loggers/RawSave.py
pnostic/loggers/ToCSV.py
pnostic/loggers/ToCSVCompressed.py
pnostic/loggers/ToJSON.py
pnostic/loggers/ToJSONL.py
pnostic/loggers/__init__.py
pnostic/providers/BaseCSV.py
pnostic/providers/Folder.py
pnostic/providers/GH.py
pnostic/providers/GH_Query.py
pnostic/providers/GenericHuggProvider.py
pnostic/providers/SingleFile.py
pnostic/providers/__init__.py
pnostic/runners/__init__.py
pnostic/runners/ollama_api.py
pnostic/runners/openai_api.py
pnostic/runners/simple.py
pnostic/seclusion/__init__.py
pnostic/seclusion/core.py
pnostic/seclusion/titan.py
pnostic-0.8.70.dist-info/LICENSE
pnostic-0.8.70.dist-info/METADATA
pnostic-0.8.70.dist-info/WHEEL
pnostic-0.8.70.dist-info/top_level.txt
pnostic-0.8.70.dist-info/RECORD
