Metadata-Version: 2.1
Name: pnostic
Version: 0.8.70
Summary: My short description for my project.
Home-page: https://github.com/franceme/pnostic
Author: Miles Frantz
Author-email: frantzme@vt.edu
Classifier: Programming Language :: Python
Classifier: Programming Language :: Python :: 3
Classifier: Programming Language :: Python :: 3.8
Requires-Python: >=3.8.0
License-File: LICENSE
Requires-Dist: ephfile
Requires-Dist: mystring
Requires-Dist: splych
Requires-Dist: hugg
Provides-Extra: all
